[
  {
    "url": "https://www.atb.com/wealth/good-advice/markets/weekly-market-update-march-30-2026/",
    "title": "Weekly Market Update - March 30, 2026 - ATB Financial",
    "language": "Italian",
    "topic": "politics",
    "has_content": true,
    "content_length": 8384
  },
  {
    "url": "https://www.blackrock.com/us/individual/insights/blackrock-investment-institute/weekly-commentary",
    "title": "Weekly market commentary | BlackRock Investment Institute",
    "language": "Italian",
    "topic": "politics",
    "has_content": true,
    "content_length": 11596
  },
  {
    "url": "https://www.eatonvance.com/insights/slimmons-take/equity-market-commentary-march-2026.html",
    "title": "Equity Market Commentary - March 2026 | Eaton Vance",
    "language": "Italian",
    "topic": "politics",
    "has_content": false,
    "content_length": 0
  },
  {
    "url": "https://www.morganstanley.com/im/publication/insights/articles/articleequitymarketcommentarymarch2026.pdf",
    "title": "Equity Market Commentary - Morgan Stanley",
    "language": "Italian",
    "topic": "politics",
    "has_content": false,
    "content_length": 0
  },
  {
    "url": "https://www.townebank.com/trust/resources/market-commentary-march-2026/",
    "title": "TowneBank | Market Commentary - March 2026",
    "language": "Italian",
    "topic": "politics",
    "has_content": true,
    "content_length": 17216
  },
  {
    "url": "https://www.stockbrokers.com/guides/free-stock-trading",
    "title": "5 Best Free Trading Platforms for 2026 - StockBrokers.com",
    "language": "Italian",
    "topic": "politics",
    "has_content": true,
    "content_length": 15095
  },
  {
    "url": "https://liveoverture.com/blog/top-stock-trading-platforms-for-seniors/",
    "title": "Top Stock Trading Platforms for Seniors | Blog | Overture",
    "language": "Italian",
    "topic": "politics",
    "has_content": true,
    "content_length": 3797
  },
  {
    "url": "https://simul8or.com/",
    "title": "simul8or - Trading Simulator - Practice Day Trading for Free - N…",
    "language": "Italian",
    "topic": "politics",
    "has_content": true,
    "content_length": 1095
  },
  {
    "url": "https://en.wikipedia.org/wiki/Olympic_National_Park",
    "title": "Olympic National Park - Wikipedia",
    "language": "Italian",
    "topic": "economics",
    "has_content": false,
    "content_length": 0
  },
  {
    "url": "https://www.nps.gov/olym/index.htm",
    "title": "Olympic National Park (U.S. National Park Service)",
    "language": "Italian",
    "topic": "economics",
    "has_content": true,
    "content_length": 1080
  },
  {
    "url": "https://www.earthtrekkers.com/best-things-to-do-in-olympic-national-park/",
    "title": "Best Things to Do in Olympic National Park (2026 Guide)",
    "language": "Italian",
    "topic": "economics",
    "has_content": true,
    "content_length": 30071
  },
  {
    "url": "https://thenatureseeker.com/olympic-national-park-washington/",
    "title": "Olympic National Park Washington: 1st Time Visitor Guide",
    "language": "Italian",
    "topic": "economics",
    "has_content": true,
    "content_length": 8216
  },
  {
    "url": "https://www.britannica.com/place/Olympic-National-Park",
    "title": "Olympic National Park | Map, Washington, & Facts | Britannica",
    "language": "Italian",
    "topic": "economics",
    "has_content": false,
    "content_length": 0
  },
  {
    "url": "https://national-parks.org/united-states/olympic/",
    "title": "Olympic National Park | (Official GANP Page)",
    "language": "Italian",
    "topic": "economics",
    "has_content": true,
    "content_length": 4259
  },
  {
    "url": "https://www.lonelyplanet.com/articles/guide-to-olympic-national-park-washington-usa",
    "title": "A first-time guide to Olympic National Park - Lonely Planet",
    "language": "Italian",
    "topic": "economics",
    "has_content": true,
    "content_length": 11794
  },
  {
    "url": "https://www.nationalgeographic.com/travel/national-parks/article/olympic-national-park",
    "title": "How to make the most of your time in Olympic National Park",
    "language": "Italian",
    "topic": "economics",
    "has_content": true,
    "content_length": 13171
  },
  {
    "url": "https://www.kitchenwarehouse.com.au/bakeware/baking-equipment/cake-tins-and-cake-pans/springform-pans",
    "title": "Springform Cake Tins - Buy a Springform Pan Online",
    "language": "Italian",
    "topic": "culture",
    "has_content": false,
    "content_length": 0
  },
  {
    "url": "https://www.bigw.com.au/home/kitchen/baking/baking-pans-trays/tart-quiche-pie-tins/c/651711710305?msockid=1df2f218bcdf686517cee534bd4b69c5",
    "title": "Tart, Quiche & Pie Tins | Home | BIG W",
    "language": "Italian",
    "topic": "culture",
    "has_content": false,
    "content_length": 0
  },
  {
    "url": "https://www.myer.com.au/c/home/all-kitchen/baking/bakeware-tins-moulds",
    "title": "Tins & Moulds | Shop Bakeware Tins & Moulds Online | MYER",
    "language": "Italian",
    "topic": "culture",
    "has_content": true,
    "content_length": 2398
  },
  {
    "url": "https://www.amazon.com.au/springform-cake-tin/s?k=springform+cake+tin",
    "title": "Amazon.com.au: Springform Cake Tin",
    "language": "Italian",
    "topic": "culture",
    "has_content": false,
    "content_length": 0
  },
  {
    "url": "https://www.rejectshop.com.au/p/non-stick-spring-form-cake-tin-22cm",
    "title": "Non-Stick Spring Form Cake Tin 22cm - The Reject Shop",
    "language": "Italian",
    "topic": "culture",
    "has_content": true,
    "content_length": 394
  },
  {
    "url": "https://myhouse.com.au/collections/kitchen-bakeware-baking-pans-springform",
    "title": "Springform Pans & More - Baking Pans - MyHouse",
    "language": "Italian",
    "topic": "culture",
    "has_content": true,
    "content_length": 571
  },
  {
    "url": "https://matchbox.com.au/collections/springform-pans",
    "title": "Springform Pans - Buy Springform Pans in Various Sizes – Matchbox",
    "language": "Italian",
    "topic": "culture",
    "has_content": true,
    "content_length": 2439
  },
  {
    "url": "https://www.corriere.it/esteri/diretta-live/26_marzo_25/guerra-in-iran-le-ultime-notizie-in-diretta.shtml",
    "title": "Guerra in Iran, le notizie del 25 marzo 2026 | Corriere.it",
    "language": "Italian",
    "topic": "culture",
    "has_content": true,
    "content_length": 67264
  },
  {
    "url": "https://www.foodnetwork.com/",
    "title": "Easy Recipes, Healthy Eating Ideas and Chef Recipe Videos | Food …",
    "language": "Italian",
    "topic": "society",
    "has_content": false,
    "content_length": 0
  },
  {
    "url": "https://www.foodnetwork.com/recipes",
    "title": "Recipes, Dinners and Easy Meal Ideas | Food Network",
    "language": "Italian",
    "topic": "society",
    "has_content": false,
    "content_length": 0
  },
  {
    "url": "https://www.foodnetwork.com/recipes/photos/food-network-kitchen-s-best-recipes",
    "title": "Food Network's Best Recipes | Food Network",
    "language": "Italian",
    "topic": "society",
    "has_content": false,
    "content_length": 0
  },
  {
    "url": "https://www.foodnetwork.com/recipes/photos/foodnetwork-top-50-most-saved-recipes",
    "title": "Food Network's Top 50 Fan-Favorite Recipes | Food Network",
    "language": "Italian",
    "topic": "society",
    "has_content": false,
    "content_length": 0
  },
  {
    "url": "https://www.foodnetwork.com/profiles",
    "title": "Food Network Chef Bios, Videos and Recipes | Food Network",
    "language": "Italian",
    "topic": "society",
    "has_content": false,
    "content_length": 0
  },
  {
    "url": "https://www.foodnetwork.com/recipes/photos/30-minute-dinner-recipes",
    "title": "103 Quick Dinner Ideas in 30 Minutes or Less | Food Network",
    "language": "Italian",
    "topic": "society",
    "has_content": false,
    "content_length": 0
  },
  {
    "url": "https://www.foodnetwork.com/recipes/recipes-a-z",
    "title": "Recipes A to Z | Recipes, Dinners and Easy Meal Ideas | Food Network",
    "language": "Italian",
    "topic": "society",
    "has_content": false,
    "content_length": 0
  },
  {
    "url": "https://www.foodnetwork.com/shows/tv-schedule",
    "title": "Food Network TV & Show Schedule",
    "language": "Italian",
    "topic": "society",
    "has_content": false,
    "content_length": 0
  }
]