[
  {
    "url": "https://fortnitetracker.com/",
    "title": "Fortnite Tracker - Fortnite Stats, Leaderboards, & More!",
    "language": "Dutch",
    "topic": "politics",
    "has_content": false,
    "content_length": 0
  },
  {
    "url": "https://www.fortnite.com/competitive/?region=NAC",
    "title": "Fortnite Competitive - Fortnite Tournaments",
    "language": "Dutch",
    "topic": "politics",
    "has_content": false,
    "content_length": 0
  },
  {
    "url": "https://blast.tv/fortnite/tournaments",
    "title": "Fortnite Competitive Tournaments - Leaderboards and more",
    "language": "Dutch",
    "topic": "politics",
    "has_content": true,
    "content_length": 5763
  },
  {
    "url": "https://fortnitetracker.gg/",
    "title": "Fortnite Tracker - Fortnite Stats, Events, Leaderboard, Items Shop",
    "language": "Dutch",
    "topic": "politics",
    "has_content": true,
    "content_length": 840
  },
  {
    "url": "https://fortnite.gg/stats",
    "title": "Fortnite Stats & Leaderboards Tracker - Fortnite.GG",
    "language": "Dutch",
    "topic": "politics",
    "has_content": false,
    "content_length": 0
  },
  {
    "url": "https://myfortnitestats.com/events",
    "title": "Fortnite Events & Tournaments Schedule | Fortnite Stats Tracker",
    "language": "Dutch",
    "topic": "politics",
    "has_content": true,
    "content_length": 2751
  },
  {
    "url": "https://www.theclick.gg/fortnite-ice-king-vs-foundation-live-tracker/",
    "title": "Fortnite Ice King vs Foundation Live Tracker Updated Daily : Who Is ...",
    "language": "Dutch",
    "topic": "politics",
    "has_content": true,
    "content_length": 3924
  },
  {
    "url": "https://tracker.gg/fortnite/leaderboards",
    "title": "Fortnite Leaderboard - - Fortnite Tracker",
    "language": "Dutch",
    "topic": "politics",
    "has_content": false,
    "content_length": 0
  },
  {
    "url": "https://finance.yahoo.com/quote/JNUG/",
    "title": "Direxion Daily Junior Gold Miners Index Bull 2X Shares (JNUG)",
    "language": "Dutch",
    "topic": "economics",
    "has_content": true,
    "content_length": 4409
  },
  {
    "url": "https://www.marketwatch.com/investing/fund/jnug",
    "title": "JNUG | Direxion Daily Junior Gold Miners Index Bull 2X ETF Overvie…",
    "language": "Dutch",
    "topic": "economics",
    "has_content": false,
    "content_length": 0
  },
  {
    "url": "https://stockanalysis.com/etf/jnug/",
    "title": "JNUG ETF Stock Price & Overview",
    "language": "Dutch",
    "topic": "economics",
    "has_content": true,
    "content_length": 3703
  },
  {
    "url": "https://www.google.com/finance/quote/JNUG:NYSEARCA",
    "title": "Direxion Daily Junior Gold Miners Idx Bull 2X ETF - Google",
    "language": "Dutch",
    "topic": "economics",
    "has_content": true,
    "content_length": 2342
  },
  {
    "url": "https://www.tradingview.com/symbols/AMEX-JNUG/",
    "title": "JNUG Stock Fund Price and Chart — AMEX:JNUG — TradingView",
    "language": "Dutch",
    "topic": "economics",
    "has_content": true,
    "content_length": 8827
  },
  {
    "url": "https://www.mlb.com/mets",
    "title": "Official New York Mets Website | MLB.com",
    "language": "Dutch",
    "topic": "economics",
    "has_content": true,
    "content_length": 484
  },
  {
    "url": "https://www.mlb.com/mets/news",
    "title": "Latest Mets News | New York Mets - MLB.com",
    "language": "Dutch",
    "topic": "economics",
    "has_content": true,
    "content_length": 7471
  },
  {
    "url": "https://www.mlb.com/mets/roster/",
    "title": "Active Roster | New York Mets - MLB.com",
    "language": "Dutch",
    "topic": "economics",
    "has_content": true,
    "content_length": 1282
  },
  {
    "url": "https://forums.x-plane.org/forums/topic/247918-weather-radar-on-toliss-planes/",
    "title": "Weather radar on toliss planes? - X-Plane.Org Forum",
    "language": "Dutch",
    "topic": "culture",
    "has_content": false,
    "content_length": 0
  },
  {
    "url": "https://forums.x-plane.org/forums/topic/317751-weather-radar/",
    "title": "Weather Radar - Questions/Rejected/NotABug - X …",
    "language": "Dutch",
    "topic": "culture",
    "has_content": false,
    "content_length": 0
  },
  {
    "url": "https://forums.x-plane.org/forums/topic/324920-live-weather-does-not-represent-irl-weather-at-all/",
    "title": "Live Weather does not represent IRL weather at all.",
    "language": "Dutch",
    "topic": "culture",
    "has_content": false,
    "content_length": 0
  },
  {
    "url": "https://forums.x-plane.org/files/file/15453-xpgfs-noaa-gfs-weather-real-weather-for-x-plane/",
    "title": "[XPGFS] NOAA GFS Weather: Real Weather For X-Plane",
    "language": "Dutch",
    "topic": "culture",
    "has_content": false,
    "content_length": 0
  },
  {
    "url": "https://forums.x-plane.org/forums/topic/176966-which-weather-plugin-is-the-best-for-xp11/",
    "title": "Which weather plugin is the best for XP11? - X-Plane.Org Forum",
    "language": "Dutch",
    "topic": "culture",
    "has_content": false,
    "content_length": 0
  },
  {
    "url": "https://stockanalysis.com/quote/psx/CJPL/",
    "title": "Crescent Jute Products (PSX:CJPL) Stock Price & Overview",
    "language": "Dutch",
    "topic": "culture",
    "has_content": true,
    "content_length": 241
  },
  {
    "url": "https://psxterminal.com/symbol/CJPL?market=REG",
    "title": "CJPL Live Price & Chart - PSX Terminal | Stock Analysis ...",
    "language": "Dutch",
    "topic": "culture",
    "has_content": true,
    "content_length": 1279
  },
  {
    "url": "https://www.tradingview.com/symbols/PSX-CJPL/",
    "title": "CJPL Stock Price and Chart — PSX:CJPL — TradingView",
    "language": "Dutch",
    "topic": "culture",
    "has_content": true,
    "content_length": 4410
  },
  {
    "url": "https://www.advil.com/our-products/advil-pain/advil-targeted-relief/",
    "title": "Advil Targeted Relief: Pain Relieving Cream | Advil",
    "language": "Dutch",
    "topic": "society",
    "has_content": true,
    "content_length": 703
  },
  {
    "url": "https://health.clevelandclinic.org/anti-inflammatory-cream",
    "title": "What Are Topical Anti-Inflammatory Creams?",
    "language": "Dutch",
    "topic": "society",
    "has_content": true,
    "content_length": 7450
  },
  {
    "url": "https://www.amazon.com/Advil-Targeted-Relief-Relieving-Powerful/dp/B0CTTLFN9G",
    "title": "Amazon.com: Advil Targeted Relief Pain Relieving Cream, Up to ...",
    "language": "Dutch",
    "topic": "society",
    "has_content": true,
    "content_length": 142
  },
  {
    "url": "https://health.usnews.com/otc/rankings/pain-relief-creams-and-gels",
    "title": "7 Best Pain Relief Creams, Pharmacists-Ranked 2025 | U.S. News",
    "language": "Dutch",
    "topic": "society",
    "has_content": false,
    "content_length": 0
  },
  {
    "url": "https://www.health.harvard.edu/pain/topical-painkillers-for-sprains-and-strains",
    "title": "Topical painkillers for sprains and strains - Harvard Health",
    "language": "Dutch",
    "topic": "society",
    "has_content": true,
    "content_length": 4757
  },
  {
    "url": "https://www.haleonhealthpartner.com/en-us/pain-relief/brands/advil/products/targeted-relief/",
    "title": "New Advil Targeted Relief | Topical Pain Reliever | Haleon ...",
    "language": "Dutch",
    "topic": "society",
    "has_content": true,
    "content_length": 4132
  },
  {
    "url": "https://www.walmart.com/ip/Advil-Targeted-Relief-Pain-Relieving-Cream-8-Hours-Powerful-Relief-Minor-Arthritis-Pain-Joint-Pain-Lower-Back-Pain-Muscle-Pain-2-3-Oz/5274352945",
    "title": "Advil Targeted Relief Pain Relieving Cream 2.3 oz Up to 8 ...",
    "language": "Dutch",
    "topic": "society",
    "has_content": true,
    "content_length": 85
  },
  {
    "url": "https://www.arthritis.org/drug-guide/medication-topics/topical-nsaids-offer-joint-pain-relief",
    "title": "Topical NSAIDs Offer Joint Pain Relief - Arthritis Foundation",
    "language": "Dutch",
    "topic": "society",
    "has_content": true,
    "content_length": 5597
  }
]