{
  "claims": [
    {
      "claim": "Malta's domestic political landscape remains dominated by the Labour Party",
      "status": "unverified",
      "source_references": [],
      "agents_supporting": [
        1
      ],
      "us_content_flag": false,
      "reasoning": "Only mentioned by Agent 1 and not traceable to any provided source articles"
    },
    {
      "claim": "Malta operates under a parliamentary system with governance structures inherited from its British colonial period",
      "status": "unverified",
      "source_references": [],
      "agents_supporting": [
        1
      ],
      "us_content_flag": false,
      "reasoning": "Only mentioned by Agent 1 and not traceable to any provided source articles"
    },
    {
      "claim": "Malta attracts particularly British visitors who have established the country as a retirement destination",
      "status": "verified",
      "source_references": [
        10
      ],
      "agents_supporting": [
        1,
        2
      ],
      "us_content_flag": false,
      "reasoning": "Mentioned by Agents 1 and 2, and traceable to source [10] which mentions 'British retirees'"
    },
    {
      "claim": "Malta's tourism sector experiences notable growth despite remaining relatively overlooked by non-European travelers",
      "status": "verified",
      "source_references": [
        10
      ],
      "agents_supporting": [
        1,
        2
      ],
      "us_content_flag": false,
      "reasoning": "Both agents mention this and it's supported by source [10] stating Malta is 'mostly ignored for almost all non-Europeans'"
    },
    {
      "claim": "Malta's cultural identity blends Italian, English, and North African influences across food, language, architecture, and social customs",
      "status": "verified",
      "source_references": [
        8,
        10
      ],
      "agents_supporting": [
        1,
        2
      ],
      "us_content_flag": false,
      "reasoning": "Mentioned by both agents and supported by sources [8] and [10] describing cultural influences"
    },
    {
      "claim": "Traditional gender roles persist where men serve as household heads while women exercise significant domestic authority",
      "status": "verified",
      "source_references": [
        9
      ],
      "agents_supporting": [
        1
      ],
      "us_content_flag": false,
      "reasoning": "Traceable to source [9] which states 'The man is the head of the family, but women often exercise power in home'"
    },
    {
      "claim": "Hospitality and generosity characterize social interactions, with arranged visits considered proper etiquette",
      "status": "verified",
      "source_references": [
        9
      ],
      "agents_supporting": [
        1
      ],
      "us_content_flag": false,
      "reasoning": "Traceable to source [9] which mentions Maltese hospitality and that 'It is polite to arrange a visit in advance'"
    },
    {
      "claim": "Dating typically begins between ages fourteen and sixteen, with formal parental introductions required before relationships are considered serious",
      "status": "verified",
      "source_references": [
        9
      ],
      "agents_supporting": [
        1
      ],
      "us_content_flag": false,
      "reasoning": "Traceable to source [9] which states 'Dating starts between age fourteen and sixteen, but are only going steady when parents have been formally introduced'"
    },
    {
      "claim": "Football serves as the most popular sport across Malta",
      "status": "verified",
      "source_references": [
        9
      ],
      "agents_supporting": [
        1
      ],
      "us_content_flag": false,
      "reasoning": "Traceable to source [9] which states 'Soccer is the most popular sport in Malta'"
    },
    {
      "claim": "Walking serves as the primary means of urban exploration, particularly in Valletta and Mdina",
      "status": "verified",
      "source_references": [
        8
      ],
      "agents_supporting": [
        2
      ],
      "us_content_flag": false,
      "reasoning": "Traceable to source [8] which states 'Malta is a great place to explore by walking, especially around Valletta' and mentions Mdina"
    },
    {
      "claim": "Valletta is a UNESCO World Heritage Site containing over 300 monuments within Europe's smallest capital",
      "status": "verified",
      "source_references": [
        10
      ],
      "agents_supporting": [
        2
      ],
      "us_content_flag": false,
      "reasoning": "Traceable to source [10] which states 'Valletta packs a big punch: it's a UNESCO World Heritage Site with over 300 monuments'"
    },
    {
      "claim": "The Ħal Saflieni Hypogeum is a 5,000-year-old subterranean necropolis discovered in 1902 that restricts daily access to 80 visitors",
      "status": "verified",
      "source_references": [
        8
      ],
      "agents_supporting": [
        2
      ],
      "us_content_flag": false,
      "reasoning": "Traceable to source [8] which describes the Hypogeum as '5000-year-old subterranean necropolis only rediscovered in 1902' with 'entry limited to 80 people per day'"
    },
    {
      "claim": "Malta International Airport serves as the primary gateway with buses and ride-sharing services for ground transportation",
      "status": "verified",
      "source_references": [
        11
      ],
      "agents_supporting": [
        2
      ],
      "us_content_flag": false,
      "reasoning": "Traceable to source [11] which mentions buses and rideshares like Uber available from Malta International Airport"
    },
    {
      "claim": "Arizona Diamondbacks players including Alek Thomas, Michael Soroka, and Nolan Arenado returned from World Baseball Classic participation",
      "status": "verified",
      "source_references": [
        3
      ],
      "agents_supporting": [
        3
      ],
      "us_content_flag": true,
      "reasoning": "Traceable to source [3] but this is US sports content unrelated to Malta"
    },
    {
      "claim": "Alek Thomas batted .267/.316/.467 with a home run for Team Mexico in the World Baseball Classic",
      "status": "verified",
      "source_references": [
        3
      ],
      "agents_supporting": [
        3
      ],
      "us_content_flag": true,
      "reasoning": "Traceable to source [3] but this is US sports content unrelated to Malta"
    },
    {
      "claim": "Pitchers Thomas Hatch, Bryce Jarvis, and Shawn Dubin were reassigned to minor league camp",
      "status": "verified",
      "source_references": [
        5
      ],
      "agents_supporting": [
        3
      ],
      "us_content_flag": true,
      "reasoning": "Traceable to source [5] but this is US sports content unrelated to Malta"
    },
    {
      "claim": "Merrill Kelly was ruled out for opening day due to injury concerns",
      "status": "verified",
      "source_references": [
        6
      ],
      "agents_supporting": [
        3
      ],
      "us_content_flag": true,
      "reasoning": "Traceable to source [6] but this is US sports content unrelated to Malta"
    },
    {
      "claim": "Gabriel Moreno was sidelined with right elbow inflammation",
      "status": "verified",
      "source_references": [
        6
      ],
      "agents_supporting": [
        3
      ],
      "us_content_flag": true,
      "reasoning": "Traceable to source [6] but this is US sports content unrelated to Malta"
    },
    {
      "claim": "Zac Gallen was designated as opening day starting pitcher",
      "status": "verified",
      "source_references": [
        6
      ],
      "agents_supporting": [
        3
      ],
      "us_content_flag": true,
      "reasoning": "Traceable to source [6] but this is US sports content unrelated to Malta"
    }
  ],
  "summary": {
    "total_claims": 19,
    "verified": 17,
    "unverified": 2,
    "us_content_flagged": 6
  }
}